Metadata-Version: 2.1
Name: columntracer
Version: 1.0.5
Summary: first version
Home-page: https://github.com/BYL4746/columntracer
License: UNKNOWN
Platform: UNKNOWN
